{"grasp_info":[{"pick_index":2,"place_index":8,"tf_map_placed":{"position":{"x":1.3288608135191455,"y":1.675619567339345,"z":-0.455580996810913},"quaternion":{"w":0.9264038192401531,"x":-4.3475591113605584e-17,"y":-3.209853418251614e-17,"z":0.37653149097685995}},"tf_tip_object":{"position":{"x":0.129,"y":-0.1070000000000002,"z":0.08500000000000002},"quaternion":{"w":0.0,"x":2.081668171172169e-16,"y":0.9999999999999999,"z":-1.4059288594026824e-32}}}],"traj_pack":[{"choice_idx":0,"commands":[{"_RESOURCE_":"SetCollisionTypeCommand","body_node_path":{"is_absolute":true,"path":["root","WorldFrame","托盘-(1)","工作空间_1","WorkspaceBody","Workspace","ContainerGroup","Box_1774946342307","box_body"]},"collision_type":"kTargetObject","prev_collision_type":"kOtherObject"}],"group_idx":0,"milestone_indices":{"cols":1,"data":{"cols":1,"data":[0],"rows":1},"rows":1},"move_type":"kJoint","name":"initial","trajectory":{"name":"","robot_name":{"brand":"","series":"","variant":""},"waypoints":[{"_RESOURCE_":"xyz::motion_solver::ExecutablePointJoint","acceleration":100,"joint":{"cols":1,"data":{"cols":1,"data":[-1.1713788579976754,-0.7460236010129924,1.9876426267203646,2.220446049250313e-15,0.3291773010875261,1.1715162232944714],"rows":6},"rows":6},"move_type":"kMoveJ","velocity":100,"zone":100}]}},{"choice_idx":0,"commands":[{"_RESOURCE_":"EnableCollisionCommand","body_node_path":{"is_absolute":true,"path":["root","WorldFrame","虚拟墙—2","Skeleton","BodyNode"]}},{"_RESOURCE_":"SetRobotPositionCommand","prev_robot_joints_":{"cols":1,"data":{"cols":1,"data":[-1.1713788579976754,-0.7460236010129924,1.9876426267203646,2.220446049250313e-15,0.3291773010875261,1.1715162232944714],"rows":6},"rows":6},"robot_joints_":{"cols":1,"data":{"cols":1,"data":[1.14907164085826,-1.2458743958901712,2.6229322181745784,8.881784197001252e-16,0.19373850451048913,1.9263889011357938],"rows":6},"rows":6}}],"group_idx":0,"milestone_indices":{"cols":1,"data":{"cols":1,"data":[0,1,2,3,4,5,6,7,8,9],"rows":10},"rows":10},"move_type":"kSmartPlanner","name":"prepick","trajectory":{"name":"kSmartPlanner-2026-03-31T09:19:25.853174657+00:00","robot_name":{"brand":"","series":"","variant":""},"waypoints":[{"_RESOURCE_":"xyz::motion_solver::ExecutablePointJoint","acceleration":100,"joint":{"cols":1,"data":{"cols":1,"data":[-1.1713788579976754,-0.7460236010129924,1.9876426267203646,2.220446049250313e-15,0.3291773010875261,1.1715162232944714],"rows":6},"rows":6},"move_type":"kMoveJ","velocity":100,"zone":100},{"_RESOURCE_":"xyz::motion_solver::ExecutablePointJoint","acceleration":100,"joint":{"cols":1,"data":{"cols":1,"data":[-0.9984499058828571,-0.939372521655314,1.8962325301038208,-1.5661821703813497e-09,0.6139362945357375,1.25926343707033],"rows":6},"rows":6},"move_type":"kMoveJ","velocity":100,"zone":100},{"_RESOURCE_":"xyz::motion_solver::ExecutablePointJoint","acceleration":100,"joint":{"cols":1,"data":{"cols":1,"data":[-0.8003024324505138,-1.1559607384540218,1.7944927590706528,-6.458540385402822e-08,0.9322644533073172,1.3584363666905617],"rows":6},"rows":6},"move_type":"kMoveJ","velocity":100,"zone":100},{"_RESOURCE_":"xyz::motion_solver::ExecutablePointJoint","acceleration":100,"joint":{"cols":1,"data":{"cols":1,"data":[-0.45087014157034083,-1.5120520865544986,1.6305167427621783,-5.148993308532404e-07,1.4523322294193945,1.5260932253225135],"rows":6},"rows":6},"move_type":"kMoveJ","velocity":100,"zone":100},{"_RESOURCE_":"xyz::motion_solver::ExecutablePointJoint","acceleration":100,"joint":{"cols":1,"data":{"cols":1,"data":[0.009595621223282558,-1.5704879749293525,1.6623411742983547,-1.2900747963873746e-07,1.4789438537583028,1.58721541212046],"rows":6},"rows":6},"move_type":"kMoveJ","velocity":100,"zone":100},{"_RESOURCE_":"xyz::motion_solver::ExecutablePointJoint","acceleration":100,"joint":{"cols":1,"data":{"cols":1,"data":[0.41051244055566216,-1.6165701638266379,1.69554090517901,4.6302219544298494e-07,1.4918277877988655,1.6408847642647841],"rows":6},"rows":6},"move_type":"kMoveJ","velocity":100,"zone":100},{"_RESOURCE_":"xyz::motion_solver::ExecutablePointJoint","acceleration":100,"joint":{"cols":1,"data":{"cols":1,"data":[0.6923313729655542,-1.6379449537687853,1.7314912347486229,1.4673275182591463e-06,1.4772563412427377,1.6796484471018633],"rows":6},"rows":6},"move_type":"kMoveJ","velocity":100,"zone":100},{"_RESOURCE_":"xyz::motion_solver::ExecutablePointJoint","acceleration":100,"joint":{"cols":1,"data":{"cols":1,"data":[0.9146013619142025,-1.6469660442333642,1.7688168636627146,2.6777706649425273e-06,1.4489572043882646,1.7109592952853196],"rows":6},"rows":6},"move_type":"kMoveJ","velocity":100,"zone":100},{"_RESOURCE_":"xyz::motion_solver::ExecutablePointJoint","acceleration":100,"joint":{"cols":1,"data":{"cols":1,"data":[1.0391754307320902,-1.446275040857233,2.194877742049197,1.3087891038983837e-08,0.8221936062679516,1.8180188304681282],"rows":6},"rows":6},"move_type":"kMoveJ","velocity":100,"zone":100},{"_RESOURCE_":"xyz::motion_solver::ExecutablePointJoint","acceleration":100,"joint":{"cols":1,"data":{"cols":1,"data":[1.14907164085826,-1.2458743958901712,2.6229322181745784,8.881784197001252e-16,0.19373850451048913,1.9263889011357938],"rows":6},"rows":6},"move_type":"kMoveJ","velocity":100,"zone":100}]}},{"choice_idx":0,"commands":[{"_RESOURCE_":"SetRobotPositionCommand","prev_robot_joints_":{"cols":1,"data":{"cols":1,"data":[1.14907164085826,-1.2458743958901712,2.6229322181745784,8.881784197001252e-16,0.19373850451048913,1.9263889011357938],"rows":6},"rows":6},"robot_joints_":{"cols":1,"data":{"cols":1,"data":[1.14907164085826,-1.0995834915244158,2.6010860221069017,-4.440892098500626e-16,0.06929379621241072,1.9263889011357946],"rows":6},"rows":6}}],"group_idx":0,"milestone_indices":{"cols":1,"data":{"cols":1,"data":[0,3],"rows":2},"rows":2},"move_type":"kLinear","name":"pick","trajectory":{"name":"pick","robot_name":{"brand":"","series":"","variant":""},"waypoints":[{"_RESOURCE_":"xyz::motion_solver::ExecutablePointJoint","acceleration":100,"joint":{"cols":1,"data":{"cols":1,"data":[1.14907164085826,-1.2458743958901712,2.6229322181745784,8.881784197001252e-16,0.19373850451048913,1.9263889011357938],"rows":6},"rows":6},"move_type":"kMoveJ","velocity":100,"zone":100},{"_RESOURCE_":"xyz::motion_solver::ExecutablePointJoint","acceleration":100,"joint":{"cols":1,"data":{"cols":1,"data":[1.14907164085826,-1.197201708571694,2.616963393696242,8.881784197001252e-16,0.1510346416703494,1.9263889011357938],"rows":6},"rows":6},"move_type":"kMoveJ","velocity":100,"zone":100},{"_RESOURCE_":"xyz::motion_solver::ExecutablePointJoint","acceleration":100,"joint":{"cols":1,"data":{"cols":1,"data":[1.14907164085826,-1.1483774292439797,2.60966898218107,8.881784197001252e-16,0.10950477385780566,1.9263889011357938],"rows":6},"rows":6},"move_type":"kMoveJ","velocity":100,"zone":100},{"_RESOURCE_":"xyz::motion_solver::ExecutablePointJoint","acceleration":100,"joint":{"cols":1,"data":{"cols":1,"data":[1.14907164085826,-1.0995834915244158,2.6010860221069017,-4.440892098500626e-16,0.06929379621241072,1.9263889011357946],"rows":6},"rows":6},"move_type":"kMoveJ","velocity":100,"zone":100}]}},{"choice_idx":0,"commands":[{"_RESOURCE_":"AttachObjectCommand","attachment_info":{"from_workspace_path":{"is_absolute":true,"path":["root","WorldFrame","托盘-(1)","工作空间_1","WorkspaceBody","Workspace","ContainerGroup"]},"object_paths":[{"is_absolute":false,"path":["Box_1774946342307"]}],"reference_object_path":{"is_absolute":false,"path":["Box_1774946342307"]},"tf_tip_reference":{"position":{"x":0.129,"y":-0.1070000000000002,"z":0.08500000000000002},"quaternion":{"w":0.0,"x":2.081668171172169e-16,"y":0.9999999999999999,"z":-1.4059288594026824e-32}},"tip_path":{"is_absolute":false,"path":["工具形态","吸盘基准面","吸取组合","tip_1"]},"to_workspace_path":{"is_absolute":true,"path":["root","WorldFrame","托盘-(0)","工作空间_0","WorkspaceBody","Workspace","ContainerGroup"]}},"children_idx":[5],"children_tfs":[{"position":{"x":0.336994,"y":0.4775060000000002,"z":0.425},"quaternion":{"w":1.0,"x":0.0,"y":0.0,"z":0.0}}]},{"_RESOURCE_":"SetRobotPositionCommand","prev_robot_joints_":{"cols":1,"data":{"cols":1,"data":[1.14907164085826,-1.0995834915244158,2.6010860221069017,-4.440892098500626e-16,0.06929379621241072,1.9263889011357938],"rows":6},"rows":6},"robot_joints_":{"cols":1,"data":{"cols":1,"data":[1.14907164085826,-1.4831211647164075,2.6318989889613107,4.440892098500626e-16,0.42201850254999407,1.9263889011357946],"rows":6},"rows":6}}],"group_idx":0,"milestone_indices":{"cols":1,"data":{"cols":1,"data":[0,6],"rows":2},"rows":2},"move_type":"kLinear","name":"postpick","trajectory":{"name":"postpick","robot_name":{"brand":"","series":"","variant":""},"waypoints":[{"_RESOURCE_":"xyz::motion_solver::ExecutablePointJoint","acceleration":100,"joint":{"cols":1,"data":{"cols":1,"data":[1.14907164085826,-1.0995834915244158,2.6010860221069017,-4.440892098500626e-16,0.06929379621241072,1.9263889011357946],"rows":6},"rows":6},"move_type":"kMoveJ","velocity":100,"zone":100},{"_RESOURCE_":"xyz::motion_solver::ExecutablePointJoint","acceleration":100,"joint":{"cols":1,"data":{"cols":1,"data":[1.14907164085826,-1.165227307409238,2.6123331219447525,0.0,0.12369051225938277,1.9263889011357946],"rows":6},"rows":6},"move_type":"kMoveJ","velocity":100,"zone":100},{"_RESOURCE_":"xyz::motion_solver::ExecutablePointJoint","acceleration":100,"joint":{"cols":1,"data":{"cols":1,"data":[1.14907164085826,-1.2308135517250776,2.6212256778274767,0.0,0.18038420069249872,1.9263889011357946],"rows":6},"rows":6},"move_type":"kMoveJ","velocity":100,"zone":100},{"_RESOURCE_":"xyz::motion_solver::ExecutablePointJoint","acceleration":100,"joint":{"cols":1,"data":{"cols":1,"data":[1.14907164085826,-1.2958846078230228,2.6276802964994372,0.0,0.23900063811848238,1.9263889011357946],"rows":6},"rows":6},"move_type":"kMoveJ","velocity":100,"zone":100},{"_RESOURCE_":"xyz::motion_solver::ExecutablePointJoint","acceleration":100,"joint":{"cols":1,"data":{"cols":1,"data":[1.14907164085826,-1.359953943441933,2.6316333325208046,0.0,0.29911693771602454,1.9263889011357946],"rows":6},"rows":6},"move_type":"kMoveJ","velocity":100,"zone":100},{"_RESOURCE_":"xyz::motion_solver::ExecutablePointJoint","acceleration":100,"joint":{"cols":1,"data":{"cols":1,"data":[1.14907164085826,-1.4225265085996044,2.633044448891088,0.0,0.3602783865034138,1.9263889011357946],"rows":6},"rows":6},"move_type":"kMoveJ","velocity":100,"zone":100},{"_RESOURCE_":"xyz::motion_solver::ExecutablePointJoint","acceleration":100,"joint":{"cols":1,"data":{"cols":1,"data":[1.14907164085826,-1.4831211647164075,2.6318989889613107,4.440892098500626e-16,0.42201850254999407,1.9263889011357946],"rows":6},"rows":6},"move_type":"kMoveJ","velocity":100,"zone":100}]}},{"choice_idx":0,"commands":[{"_RESOURCE_":"EnableCollisionCommand","body_node_path":{"is_absolute":true,"path":["root","WorldFrame","长方体-(3)","Skeleton","BodyNode"]}},{"_RESOURCE_":"SetRobotPositionCommand","prev_robot_joints_":{"cols":1,"data":{"cols":1,"data":[1.14907164085826,-1.4831211647164075,2.6318989889613107,4.440892098500626e-16,0.42201850254999407,1.9263889011357938],"rows":6},"rows":6},"robot_joints_":{"cols":1,"data":{"cols":1,"data":[-0.9003278859965644,-0.21464417321839369,0.7961633936503487,0.0,0.989277106362942,-0.12822913149931825],"rows":6},"rows":6}}],"group_idx":0,"milestone_indices":{"cols":1,"data":{"cols":1,"data":[0,1,2,3,4,5,6,7,8,9],"rows":10},"rows":10},"move_type":"kSmartPlanner","name":"slidestart_z","trajectory":{"name":"kSmartPlanner-2026-03-31T09:19:26.478715557+00:00","robot_name":{"brand":"","series":"","variant":""},"waypoints":[{"_RESOURCE_":"xyz::motion_solver::ExecutablePointJoint","acceleration":100,"joint":{"cols":1,"data":{"cols":1,"data":[1.14907164085826,-1.4831211647164075,2.6318989889613107,4.440892098500626e-16,0.42201850254999407,1.9263889011357946],"rows":6},"rows":6},"move_type":"kMoveJ","velocity":100,"zone":100},{"_RESOURCE_":"xyz::motion_solver::ExecutablePointJoint","acceleration":100,"joint":{"cols":1,"data":{"cols":1,"data":[1.0908527961354235,-1.6481771561254452,2.1503977044182907,-5.855617025096233e-08,1.0685758016614695,1.6470787061317813],"rows":6},"rows":6},"move_type":"kMoveJ","velocity":100,"zone":100},{"_RESOURCE_":"xyz::motion_solver::ExecutablePointJoint","acceleration":100,"joint":{"cols":1,"data":{"cols":1,"data":[0.9485483443933911,-1.6872128829068478,1.8266943584514361,2.42565900110526e-06,1.4313344127151275,1.386860308413027],"rows":6},"rows":6},"move_type":"kMoveJ","velocity":100,"zone":100},{"_RESOURCE_":"xyz::motion_solver::ExecutablePointJoint","acceleration":100,"joint":{"cols":1,"data":{"cols":1,"data":[0.6424412958389263,-1.6459757838719429,1.6361981358234081,3.7400054789960104e-07,1.5805754678822288,1.1246896151816406],"rows":6},"rows":6},"move_type":"kMoveJ","velocity":100,"zone":100},{"_RESOURCE_":"xyz::motion_solver::ExecutablePointJoint","acceleration":100,"joint":{"cols":1,"data":{"cols":1,"data":[-0.013859774185358928,-1.4617683321230008,1.4191599134817972,8.608612740585883e-08,1.6134050695858164,0.6795873312807041],"rows":6},"rows":6},"move_type":"kMoveJ","velocity":100,"zone":100},{"_RESOURCE_":"xyz::motion_solver::ExecutablePointJoint","acceleration":100,"joint":{"cols":1,"data":{"cols":1,"data":[-0.29985532376680624,-1.3621300848594586,1.3245325643775598,9.080302262725082e-09,1.6083938416119143,0.47973526551876544],"rows":6},"rows":6},"move_type":"kMoveJ","velocity":100,"zone":100},{"_RESOURCE_":"xyz::motion_solver::ExecutablePointJoint","acceleration":100,"joint":{"cols":1,"data":{"cols":1,"data":[-0.4702407403912188,-1.2820298169030617,1.2681048196299163,1.5097323254581817e-08,1.5847213141937366,0.35436288840263785],"rows":6},"rows":6},"move_type":"kMoveJ","velocity":100,"zone":100},{"_RESOURCE_":"xyz::motion_solver::ExecutablePointJoint","acceleration":100,"joint":{"cols":1,"data":{"cols":1,"data":[-0.6238902844611436,-0.9284623315894078,1.110868829908606,-9.172155454059331e-09,1.3883898203376404,0.19364053699205308],"rows":6},"rows":6},"move_type":"kMoveJ","velocity":100,"zone":100},{"_RESOURCE_":"xyz::motion_solver::ExecutablePointJoint","acceleration":100,"joint":{"cols":1,"data":{"cols":1,"data":[-0.7621047080804189,-0.5715532208746356,0.9535161113964766,3.703874871423815e-10,1.188833436459769,0.03270570326351163],"rows":6},"rows":6},"move_type":"kMoveJ","velocity":100,"zone":100},{"_RESOURCE_":"xyz::motion_solver::ExecutablePointJoint","acceleration":100,"joint":{"cols":1,"data":{"cols":1,"data":[-0.9003278859965644,-0.21464417321839369,0.7961633936503487,0.0,0.989277106362942,-0.12822913149931825],"rows":6},"rows":6},"move_type":"kMoveJ","velocity":100,"zone":100}]}},{"choice_idx":1,"commands":[{"_RESOURCE_":"SetRobotPositionCommand","prev_robot_joints_":{"cols":1,"data":{"cols":1,"data":[-0.9003278859965644,-0.21464417321839369,0.7961633936503487,0.0,0.989277106362942,-0.12822913149931825],"rows":6},"rows":6},"robot_joints_":{"cols":1,"data":{"cols":1,"data":[-0.9003278859965644,-0.18122321844828937,0.7758378024279846,0.0,0.9761817428152009,-0.12822913149931825],"rows":6},"rows":6}}],"group_idx":0,"milestone_indices":{"cols":1,"data":{"cols":1,"data":[0,1],"rows":2},"rows":2},"move_type":"kLinear","name":"slidestart","trajectory":{"name":"slidestart","robot_name":{"brand":"","series":"","variant":""},"waypoints":[{"_RESOURCE_":"xyz::motion_solver::ExecutablePointJoint","acceleration":100,"joint":{"cols":1,"data":{"cols":1,"data":[-0.9003278859965644,-0.21464417321839369,0.7961633936503487,0.0,0.989277106362942,-0.12822913149931825],"rows":6},"rows":6},"move_type":"kMoveJ","velocity":100,"zone":100},{"_RESOURCE_":"xyz::motion_solver::ExecutablePointJoint","acceleration":100,"joint":{"cols":1,"data":{"cols":1,"data":[-0.9003278859965644,-0.18122321844828937,0.7758378024279846,0.0,0.9761817428152009,-0.12822913149931825],"rows":6},"rows":6},"move_type":"kMoveJ","velocity":100,"zone":100}]}},{"choice_idx":0,"commands":[{"_RESOURCE_":"DisableCollisionCommand","body_node_path":{"is_absolute":true,"path":["root","WorldFrame","虚拟墙—2","Skeleton","BodyNode"]}},{"_RESOURCE_":"SetRobotPositionCommand","prev_robot_joints_":{"cols":1,"data":{"cols":1,"data":[-0.9003278859965644,-0.18122321844828937,0.7758378024279846,0.0,0.9761817428152009,-0.12822913149931825],"rows":6},"rows":6},"robot_joints_":{"cols":1,"data":{"cols":1,"data":[-0.9003278859965644,-0.18122321844828848,0.7758378024279837,0.0,0.9761817428152018,-0.12822913149932358],"rows":6},"rows":6}}],"group_idx":0,"milestone_indices":{"cols":1,"data":{"cols":1,"data":[0,1],"rows":2},"rows":2},"move_type":"kJoint","name":"preplace","trajectory":{"name":"preplace","robot_name":{"brand":"","series":"","variant":""},"waypoints":[{"_RESOURCE_":"xyz::motion_solver::ExecutablePointJoint","acceleration":100,"joint":{"cols":1,"data":{"cols":1,"data":[-0.9003278859965644,-0.18122321844828937,0.7758378024279846,0.0,0.9761817428152009,-0.12822913149931825],"rows":6},"rows":6},"move_type":"kMoveJ","velocity":100,"zone":100},{"_RESOURCE_":"xyz::motion_solver::ExecutablePointJoint","acceleration":100,"joint":{"cols":1,"data":{"cols":1,"data":[-0.9003278859965644,-0.18122321844828848,0.7758378024279837,0.0,0.9761817428152018,-0.12822913149932358],"rows":6},"rows":6},"move_type":"kMoveJ","velocity":100,"zone":100}]}},{"choice_idx":1,"commands":[{"_RESOURCE_":"SetRobotPositionCommand","prev_robot_joints_":{"cols":1,"data":{"cols":1,"data":[-0.9003278859965644,-0.18122321844828937,0.7758378024279846,0.0,0.9761817428152009,-0.12822913149931825],"rows":6},"rows":6},"robot_joints_":{"cols":1,"data":{"cols":1,"data":[-0.9295601545098933,-0.20960445471704414,0.8796426541556741,0.0,0.9007581273562666,-0.15746140001264708],"rows":6},"rows":6}}],"group_idx":0,"milestone_indices":{"cols":1,"data":{"cols":1,"data":[0,20],"rows":2},"rows":2},"move_type":"kLinear","name":"near_place","trajectory":{"name":"near_place","robot_name":{"brand":"","series":"","variant":""},"waypoints":[{"_RESOURCE_":"xyz::motion_solver::ExecutablePointJoint","acceleration":100,"joint":{"cols":1,"data":{"cols":1,"data":[-0.9003278859965644,-0.18122321844828848,0.7758378024279837,0.0,0.9761817428152018,-0.12822913149932358],"rows":6},"rows":6},"move_type":"kMoveJ","velocity":100,"zone":100},{"_RESOURCE_":"xyz::motion_solver::ExecutablePointJoint","acceleration":100,"joint":{"cols":1,"data":{"cols":1,"data":[-0.9017592362625266,-0.18297635106248578,0.7816232426770915,0.0,0.9721494351802917,-0.12966048176528533],"rows":6},"rows":6},"move_type":"kMoveJ","velocity":100,"zone":100},{"_RESOURCE_":"xyz::motion_solver::ExecutablePointJoint","acceleration":100,"joint":{"cols":1,"data":{"cols":1,"data":[-0.9031937457019499,-0.18468965737089071,0.7873372678010058,0.0,0.9681487163647828,-0.1310949912047108],"rows":6},"rows":6},"move_type":"kMoveJ","velocity":100,"zone":100},{"_RESOURCE_":"xyz::motion_solver::ExecutablePointJoint","acceleration":100,"joint":{"cols":1,"data":{"cols":1,"data":[-0.9046314188619511,-0.186364063556669,0.7929816224278068,0.0,0.9641787679237597,-0.13253266436471156],"rows":6},"rows":6},"move_type":"kMoveJ","velocity":100,"zone":100},{"_RESOURCE_":"xyz::motion_solver::ExecutablePointJoint","acceleration":100,"joint":{"cols":1,"data":{"cols":1,"data":[-0.9060722602574138,-0.18800045359630868,0.7985579709388615,0.0,0.9602388094523446,-0.1339735057601712],"rows":6},"rows":6},"move_type":"kMoveJ","velocity":100,"zone":100},{"_RESOURCE_":"xyz::motion_solver::ExecutablePointJoint","acceleration":100,"joint":{"cols":1,"data":{"cols":1,"data":[-0.9075162743705225,-0.18959967190602933,0.8040679024825712,0.0,0.9563280962183551,-0.135417519873283],"rows":6},"rows":6},"move_type":"kMoveJ","velocity":100,"zone":100},{"_RESOURCE_":"xyz::motion_solver::ExecutablePointJoint","acceleration":100,"joint":{"cols":1,"data":{"cols":1,"data":[-0.9089634656502992,-0.19116252577893977,0.8095129355916852,0.0,0.9524459169821515,-0.13686471115305654],"rows":6},"rows":6},"move_type":"kMoveJ","velocity":100,"zone":100},{"_RESOURCE_":"xyz::motion_solver::ExecutablePointJoint","acceleration":100,"joint":{"cols":1,"data":{"cols":1,"data":[-0.9104138385121305,-0.19268978763283862,0.8148945224418473,0.0,0.9485915919858883,-0.1383150840148879],"rows":6},"rows":6},"move_type":"kMoveJ","velocity":100,"zone":100},{"_RESOURCE_":"xyz::motion_solver::ExecutablePointJoint","acceleration":100,"joint":{"cols":1,"data":{"cols":1,"data":[-0.9118673973372973,-0.1941821970863451,0.8202140527849098,0.0,0.9447644710963319,-0.13976864284005552],"rows":6},"rows":6},"move_type":"kMoveJ","velocity":100,"zone":100},{"_RESOURCE_":"xyz::motion_solver::ExecutablePointJoint","acceleration":100,"joint":{"cols":1,"data":{"cols":1,"data":[-0.9133241464724975,-0.1956404628791515,0.8254728575869001,0.0,0.9409639320871479,-0.14122539197525308],"rows":6},"rows":6},"move_type":"kMoveJ","velocity":100,"zone":100},{"_RESOURCE_":"xyz::motion_solver::ExecutablePointJoint","acceleration":100,"joint":{"cols":1,"data":{"cols":1,"data":[-0.9147840902293702,-0.19706526465045826,0.8306722123973032,0.0,0.9371893790480526,-0.14268533573212716],"rows":6},"rows":6},"move_type":"kMoveJ","velocity":100,"zone":100},{"_RESOURCE_":"xyz::motion_solver::ExecutablePointJoint","acceleration":100,"joint":{"cols":1,"data":{"cols":1,"data":[-0.9162472328840119,-0.19845725458823216,0.8358133404735963,0.0,0.9334402409095333,-0.14414847838676748],"rows":6},"rows":6},"move_type":"kMoveJ","velocity":100,"zone":100},{"_RESOURCE_":"xyz::motion_solver::ExecutablePointJoint","acceleration":100,"joint":{"cols":1,"data":{"cols":1,"data":[-0.9177135786764925,-0.1998170589605528,0.8408974156823801,0.0,0.9297159700730697,-0.14561482417925165],"rows":6},"rows":6},"move_type":"kMoveJ","velocity":100,"zone":100},{"_RESOURCE_":"xyz::motion_solver::ExecutablePointJoint","acceleration":100,"joint":{"cols":1,"data":{"cols":1,"data":[-0.91918313181037,-0.20114527953922234,0.8459255651963797,0.0,0.9260160411377392,-0.14708437731312562],"rows":6},"rows":6},"move_type":"kMoveJ","velocity":100,"zone":100},{"_RESOURCE_":"xyz::motion_solver::ExecutablePointJoint","acceleration":100,"joint":{"cols":1,"data":{"cols":1,"data":[-0.9206558964521983,-0.2024424949247723,0.8508988720046253,0.0,0.9223399497150435,-0.14855714195495207],"rows":6},"rows":6},"move_type":"kMoveJ","velocity":100,"zone":100},{"_RESOURCE_":"xyz::motion_solver::ExecutablePointJoint","acceleration":100,"joint":{"cols":1,"data":{"cols":1,"data":[-0.9221318767310347,-0.2037092617810834,0.8558183772513779,0.0,0.9186872113246016,-0.1500331222337885],"rows":6},"rows":6},"move_type":"kMoveJ","velocity":100,"zone":100},{"_RESOURCE_":"xyz::motion_solver::ExecutablePointJoint","acceleration":100,"joint":{"cols":1,"data":{"cols":1,"data":[-0.9236110767379442,-0.20494611598706758,0.8606850824179109,0.0,0.9150573603640533,-0.15151232224070021],"rows":6},"rows":6},"move_type":"kMoveJ","velocity":100,"zone":100},{"_RESOURCE_":"xyz::motion_solver::ExecutablePointJoint","acceleration":100,"joint":{"cols":1,"data":{"cols":1,"data":[-0.9250935005255028,-0.2061535737121183,0.8654999513598529,0.0,0.9114499491471619,-0.1529947460282548],"rows":6},"rows":6},"move_type":"kMoveJ","velocity":100,"zone":100},{"_RESOURCE_":"xyz::motion_solver::ExecutablePointJoint","acceleration":100,"joint":{"cols":1,"data":{"cols":1,"data":[-0.926579152107291,-0.20733213242142412,0.8702639122116427,0.0,0.907864547004678,-0.15448039761004484],"rows":6},"rows":6},"move_type":"kMoveJ","velocity":100,"zone":100},{"_RESOURCE_":"xyz::motion_solver::ExecutablePointJoint","acceleration":100,"joint":{"cols":1,"data":{"cols":1,"data":[-0.928068035457394,-0.20848227181665413,0.8749778591685349,0.0,0.9043007394430163,-0.15596928096015183],"rows":6},"rows":6},"move_type":"kMoveJ","velocity":100,"zone":100},{"_RESOURCE_":"xyz::motion_solver::ExecutablePointJoint","acceleration":100,"joint":{"cols":1,"data":{"cols":1,"data":[-0.9295601545098933,-0.20960445471704414,0.8796426541556741,0.0,0.9007581273562666,-0.15746140001264708],"rows":6},"rows":6},"move_type":"kMoveJ","velocity":100,"zone":100}]}},{"choice_idx":0,"commands":[{"_RESOURCE_":"SetRobotPositionCommand","prev_robot_joints_":{"cols":1,"data":{"cols":1,"data":[-0.9295601545098933,-0.20960445471704414,0.8796426541556741,0.0,0.9007581273562666,-0.15746140001264708],"rows":6},"rows":6},"robot_joints_":{"cols":1,"data":{"cols":1,"data":[-0.9395905881417006,-0.2210523792946586,0.9125208013775188,0.0,0.8793279047120368,-0.1674918336444513],"rows":6},"rows":6}}],"group_idx":0,"milestone_indices":{"cols":1,"data":{"cols":1,"data":[0,1],"rows":2},"rows":2},"move_type":"kLinear","name":"place","trajectory":{"name":"place","robot_name":{"brand":"","series":"","variant":""},"waypoints":[{"_RESOURCE_":"xyz::motion_solver::ExecutablePointJoint","acceleration":100,"joint":{"cols":1,"data":{"cols":1,"data":[-0.9295601545098933,-0.20960445471704414,0.8796426541556741,0.0,0.9007581273562666,-0.15746140001264708],"rows":6},"rows":6},"move_type":"kMoveJ","velocity":100,"zone":100},{"_RESOURCE_":"xyz::motion_solver::ExecutablePointJoint","acceleration":100,"joint":{"cols":1,"data":{"cols":1,"data":[-0.9395905881417006,-0.2210523792946586,0.9125208013775188,0.0,0.8793279047120368,-0.1674918336444513],"rows":6},"rows":6},"move_type":"kMoveJ","velocity":100,"zone":100}]}},{"choice_idx":0,"commands":[{"_RESOURCE_":"DetachObjectCommand","attachment_info":{"from_workspace_path":{"is_absolute":true,"path":["root","WorldFrame","托盘-(1)","工作空间_1","WorkspaceBody","Workspace","ContainerGroup"]},"object_paths":[{"is_absolute":false,"path":["Box_1774946342307"]}],"reference_object_path":{"is_absolute":false,"path":["Box_1774946342307"]},"tf_tip_reference":{"position":{"x":0.129,"y":-0.1070000000000002,"z":0.08500000000000002},"quaternion":{"w":0.0,"x":2.081668171172169e-16,"y":0.9999999999999999,"z":-1.4059288594026824e-32}},"tip_path":{"is_absolute":false,"path":["工具形态","吸盘基准面","吸取组合","tip_1"]},"to_workspace_path":{"is_absolute":true,"path":["root","WorldFrame","托盘-(0)","工作空间_0","WorkspaceBody","Workspace","ContainerGroup"]}},"children_idx":[0],"children_tfs":[{"position":{"x":0.129,"y":-0.10700000000000032,"z":0.08500000000000002},"quaternion":{"w":0.0,"x":0.0,"y":1.0,"z":0.0}}],"tf_new_ws_ref":{"position":{"x":0.43000000000000005,"y":0.04999999999999999,"z":0.279},"quaternion":{"w":0.9999999999999997,"x":-1.2711137632955762e-32,"y":1.2325951644078315e-32,"z":-5.551115123125788e-17}}},{"_RESOURCE_":"SetRobotPositionCommand","prev_robot_joints_":{"cols":1,"data":{"cols":1,"data":[-0.9395905881417006,-0.2210523792946586,0.9125208013775188,0.0,0.8793279047120368,-0.1674918336444513],"rows":6},"rows":6},"robot_joints_":{"cols":1,"data":{"cols":1,"data":[-0.9295601545098933,-0.20960445471704414,0.8796426541556741,0.0,0.9007581273562666,-0.15746140001265152],"rows":6},"rows":6}}],"group_idx":0,"milestone_indices":{"cols":1,"data":{"cols":1,"data":[0,1],"rows":2},"rows":2},"move_type":"kLinear","name":"nearpostplace","trajectory":{"name":"nearpostplace","robot_name":{"brand":"","series":"","variant":""},"waypoints":[{"_RESOURCE_":"xyz::motion_solver::ExecutablePointJoint","acceleration":100,"joint":{"cols":1,"data":{"cols":1,"data":[-0.9395905881417006,-0.2210523792946586,0.9125208013775188,0.0,0.8793279047120368,-0.1674918336444513],"rows":6},"rows":6},"move_type":"kMoveJ","velocity":100,"zone":100},{"_RESOURCE_":"xyz::motion_solver::ExecutablePointJoint","acceleration":100,"joint":{"cols":1,"data":{"cols":1,"data":[-0.9295601545098933,-0.20960445471704414,0.8796426541556741,0.0,0.9007581273562666,-0.15746140001265152],"rows":6},"rows":6},"move_type":"kMoveJ","velocity":100,"zone":100}]}},{"choice_idx":0,"commands":[{"_RESOURCE_":"DisableCollisionCommand","body_node_path":{"is_absolute":true,"path":["root","WorldFrame","长方体-(3)","Skeleton","BodyNode"]}},{"_RESOURCE_":"SetRobotPositionCommand","prev_robot_joints_":{"cols":1,"data":{"cols":1,"data":[-0.9295601545098933,-0.20960445471704414,0.8796426541556741,0.0,0.9007581273562666,-0.15746140001265152],"rows":6},"rows":6},"robot_joints_":{"cols":1,"data":{"cols":1,"data":[-0.9003278859965644,-0.18122321844828848,0.7758378024279837,0.0,0.9761817428152018,-0.1282291314993249],"rows":6},"rows":6}},{"_RESOURCE_":"SetCollisionTypeCommand","body_node_path":{"is_absolute":true,"path":["root","WorldFrame","托盘-(0)","工作空间_0","WorkspaceBody","Workspace","ContainerGroup","Box_1774946342307","box_body"]},"collision_type":"kOtherObject","prev_collision_type":"kTargetObject"}],"group_idx":0,"milestone_indices":{"cols":1,"data":{"cols":1,"data":[0,2],"rows":2},"rows":2},"move_type":"kLinear","name":"postplace","trajectory":{"name":"postplace","robot_name":{"brand":"","series":"","variant":""},"waypoints":[{"_RESOURCE_":"xyz::motion_solver::ExecutablePointJoint","acceleration":100,"joint":{"cols":1,"data":{"cols":1,"data":[-0.9295601545098933,-0.20960445471704414,0.8796426541556741,0.0,0.9007581273562666,-0.15746140001265152],"rows":6},"rows":6},"move_type":"kMoveJ","velocity":100,"zone":100},{"_RESOURCE_":"xyz::motion_solver::ExecutablePointJoint","acceleration":100,"joint":{"cols":1,"data":{"cols":1,"data":[-0.9147840902293707,-0.19706526465045782,0.8306722123973014,0.0,0.9371893790480534,-0.14268533573212228],"rows":6},"rows":6},"move_type":"kMoveJ","velocity":100,"zone":100},{"_RESOURCE_":"xyz::motion_solver::ExecutablePointJoint","acceleration":100,"joint":{"cols":1,"data":{"cols":1,"data":[-0.9003278859965644,-0.18122321844828848,0.7758378024279837,0.0,0.9761817428152018,-0.1282291314993249],"rows":6},"rows":6},"move_type":"kMoveJ","velocity":100,"zone":100}]}}]}