{"grasp_info":[{"pick_index":2,"place_index":8,"tf_map_placed":{"position":{"x":-1.6222724442128706,"y":-1.011913021108226,"z":-0.3785000190734863},"quaternion":{"w":0.9238795325112875,"x":7.170160890364024e-17,"y":3.716025912496974e-17,"z":0.3826834323650908}},"tf_tip_object":{"position":{"x":-0.1280000000000001,"y":-0.12150000000000011,"z":0.12450000000000011},"quaternion":{"w":-1.8055593228630333e-32,"x":1.0000000000000002,"y":-2.081668171172168e-16,"z":1.2325951644078307e-32}}}],"traj_pack":[{"choice_idx":0,"commands":[{"_RESOURCE_":"SetCollisionTypeCommand","body_node_path":{"is_absolute":true,"path":["root","WorldFrame","托盘-(1)","工作空间_1","WorkspaceBody","Workspace","ContainerGroup","Box_1774946344618","box_body"]},"collision_type":"kTargetObject","prev_collision_type":"kOtherObject"}],"group_idx":0,"milestone_indices":{"cols":1,"data":{"cols":1,"data":[0],"rows":1},"rows":1},"move_type":"kJoint","name":"initial","trajectory":{"name":"","robot_name":{"brand":"","series":"","variant":""},"waypoints":[{"_RESOURCE_":"xyz::motion_solver::ExecutablePointJoint","acceleration":100,"joint":{"cols":1,"data":{"cols":1,"data":[2.7268831946703234,-0.7130088201458884,1.7339085007934631,0.0,0.5498966461473218,0.3706887044779732],"rows":6},"rows":6},"move_type":"kMoveJ","velocity":100,"zone":100}]}},{"choice_idx":0,"commands":[{"_RESOURCE_":"SetRobotPositionCommand","prev_robot_joints_":{"cols":1,"data":{"cols":1,"data":[2.7268831946703234,-0.7130088201458884,1.7339085007934631,0.0,0.5498966461473218,0.3706887044779732],"rows":6},"rows":6},"robot_joints_":{"cols":1,"data":{"cols":1,"data":[0.9538992599515632,-1.9835330397546578,2.4320543876148104,0.0,1.122274978934744,0.160420193434192],"rows":6},"rows":6}}],"group_idx":0,"milestone_indices":{"cols":1,"data":{"cols":1,"data":[0,1,2,3,4,5,6],"rows":7},"rows":7},"move_type":"kSmartPlanner","name":"prepick","trajectory":{"name":"kSmartPlanner-2026-03-31T09:38:17.103032526+00:00","robot_name":{"brand":"","series":"","variant":""},"waypoints":[{"_RESOURCE_":"xyz::motion_solver::ExecutablePointJoint","acceleration":100,"joint":{"cols":1,"data":{"cols":1,"data":[2.7268831946703234,-0.7130088201458884,1.7339085007934631,0.0,0.5498966461473218,0.3706887044779732],"rows":6},"rows":6},"move_type":"kMoveJ","velocity":100,"zone":100},{"_RESOURCE_":"xyz::motion_solver::ExecutablePointJoint","acceleration":100,"joint":{"cols":1,"data":{"cols":1,"data":[2.648148312828596,-0.7955567045442911,1.7609299601007085,-2.6773715327918054e-11,0.6054230717886548,0.3570333460251758],"rows":6},"rows":6},"move_type":"kMoveJ","velocity":100,"zone":100},{"_RESOURCE_":"xyz::motion_solver::ExecutablePointJoint","acceleration":100,"joint":{"cols":1,"data":{"cols":1,"data":[2.495350401295357,-0.9553506623123897,1.813417967845083,1.4131405537830077e-07,0.7127290194065172,0.3305360484264725],"rows":6},"rows":6},"move_type":"kMoveJ","velocity":100,"zone":100},{"_RESOURCE_":"xyz::motion_solver::ExecutablePointJoint","acceleration":100,"joint":{"cols":1,"data":{"cols":1,"data":[2.1345468049831444,-1.3309791345281845,1.937639901745158,5.769004985288383e-07,0.9641355006567979,0.2679538476401906],"rows":6},"rows":6},"move_type":"kMoveJ","velocity":100,"zone":100},{"_RESOURCE_":"xyz::motion_solver::ExecutablePointJoint","acceleration":100,"joint":{"cols":1,"data":{"cols":1,"data":[1.9262789520185766,-1.5293909346819465,2.012678850682044,1.8422008245458635e-07,1.0875076297344084,0.23158302305129702],"rows":6},"rows":6},"move_type":"kMoveJ","velocity":100,"zone":100},{"_RESOURCE_":"xyz::motion_solver::ExecutablePointJoint","acceleration":100,"joint":{"cols":1,"data":{"cols":1,"data":[1.196930028468801,-1.8699857068230172,2.3272319686038325,1.780816759360665e-08,1.113549674739922,0.1782143997103614],"rows":6},"rows":6},"move_type":"kMoveJ","velocity":100,"zone":100},{"_RESOURCE_":"xyz::motion_solver::ExecutablePointJoint","acceleration":100,"joint":{"cols":1,"data":{"cols":1,"data":[0.9538992599515632,-1.9835330397546578,2.4320543876148104,0.0,1.122274978934744,0.160420193434192],"rows":6},"rows":6},"move_type":"kMoveJ","velocity":100,"zone":100}]}},{"choice_idx":2,"commands":[{"_RESOURCE_":"SetRobotPositionCommand","prev_robot_joints_":{"cols":1,"data":{"cols":1,"data":[0.9538992599515632,-1.9835330397546578,2.4320543876148104,0.0,1.122274978934744,0.160420193434192],"rows":6},"rows":6},"robot_joints_":{"cols":1,"data":{"cols":1,"data":[0.9538992599515632,-1.936496790005331,2.4903934244147106,0.0,1.0168996923855183,0.16042019343419778],"rows":6},"rows":6}}],"group_idx":0,"milestone_indices":{"cols":1,"data":{"cols":1,"data":[0,3],"rows":2},"rows":2},"move_type":"kLinear","name":"pick","trajectory":{"name":"pick","robot_name":{"brand":"","series":"","variant":""},"waypoints":[{"_RESOURCE_":"xyz::motion_solver::ExecutablePointJoint","acceleration":100,"joint":{"cols":1,"data":{"cols":1,"data":[0.9538992599515632,-1.9835330397546578,2.4320543876148104,0.0,1.122274978934744,0.160420193434192],"rows":6},"rows":6},"move_type":"kMoveJ","velocity":100,"zone":100},{"_RESOURCE_":"xyz::motion_solver::ExecutablePointJoint","acceleration":100,"joint":{"cols":1,"data":{"cols":1,"data":[0.9538992599515632,-1.9695242397532398,2.452290742503152,0.0,1.0880298240449848,0.160420193434196],"rows":6},"rows":6},"move_type":"kMoveJ","velocity":100,"zone":100},{"_RESOURCE_":"xyz::motion_solver::ExecutablePointJoint","acceleration":100,"joint":{"cols":1,"data":{"cols":1,"data":[0.9538992599515632,-1.9538697321405156,2.471749583508096,0.0,1.052916475427315,0.160420193434196],"rows":6},"rows":6},"move_type":"kMoveJ","velocity":100,"zone":100},{"_RESOURCE_":"xyz::motion_solver::ExecutablePointJoint","acceleration":100,"joint":{"cols":1,"data":{"cols":1,"data":[0.9538992599515632,-1.936496790005331,2.4903934244147106,0.0,1.0168996923855183,0.16042019343419778],"rows":6},"rows":6},"move_type":"kMoveJ","velocity":100,"zone":100}]}},{"choice_idx":0,"commands":[{"_RESOURCE_":"AttachObjectCommand","attachment_info":{"from_workspace_path":{"is_absolute":true,"path":["root","WorldFrame","托盘-(1)","工作空间_1","WorkspaceBody","Workspace","ContainerGroup"]},"object_paths":[{"is_absolute":false,"path":["Box_1774946344618"]}],"reference_object_path":{"is_absolute":false,"path":["Box_1774946344618"]},"tf_tip_reference":{"position":{"x":-0.1280000000000001,"y":-0.12150000000000011,"z":0.12450000000000011},"quaternion":{"w":-1.8055593228630333e-32,"x":1.0000000000000002,"y":-2.081668171172168e-16,"z":1.2325951644078307e-32}},"tip_path":{"is_absolute":false,"path":["工具形态","吸盘基准面","吸取组合","tip_1"]},"to_workspace_path":{"is_absolute":true,"path":["root","WorldFrame","托盘-(3)","工作空间_3","WorkspaceBody","Workspace","ContainerGroup"]}},"children_idx":[7],"children_tfs":[{"position":{"x":0.51899595,"y":0.41999481000000005,"z":1.1205},"quaternion":{"w":0.7071067811865476,"x":0.0,"y":0.0,"z":0.7071067811865475}}]},{"_RESOURCE_":"SetRobotPositionCommand","prev_robot_joints_":{"cols":1,"data":{"cols":1,"data":[0.9538992599515632,-1.936496790005331,2.4903934244147106,0.0,1.0168996923855183,0.160420193434192],"rows":6},"rows":6},"robot_joints_":{"cols":1,"data":{"cols":1,"data":[0.9538992599515632,-2.0430703931865377,2.2600169406236343,0.0,1.3538497793578008,0.16042019343420044],"rows":6},"rows":6}}],"group_idx":0,"milestone_indices":{"cols":1,"data":{"cols":1,"data":[0,7],"rows":2},"rows":2},"move_type":"kLinear","name":"postpick","trajectory":{"name":"postpick","robot_name":{"brand":"","series":"","variant":""},"waypoints":[{"_RESOURCE_":"xyz::motion_solver::ExecutablePointJoint","acceleration":100,"joint":{"cols":1,"data":{"cols":1,"data":[0.9538992599515632,-1.936496790005331,2.4903934244147106,0.0,1.0168996923855183,0.16042019343419778],"rows":6},"rows":6},"move_type":"kMoveJ","velocity":100,"zone":100},{"_RESOURCE_":"xyz::motion_solver::ExecutablePointJoint","acceleration":100,"joint":{"cols":1,"data":{"cols":1,"data":[0.9538992599515632,-1.9617730523702421,2.4622864007768808,0.0,1.07028297838826,0.1604201934341991],"rows":6},"rows":6},"move_type":"kMoveJ","velocity":100,"zone":100},{"_RESOURCE_":"xyz::motion_solver::ExecutablePointJoint","acceleration":100,"joint":{"cols":1,"data":{"cols":1,"data":[0.9538992599515632,-1.9833063454279194,2.432407650249216,0.0,1.1216950219736015,0.16042019343419778],"rows":6},"rows":6},"move_type":"kMoveJ","velocity":100,"zone":100},{"_RESOURCE_":"xyz::motion_solver::ExecutablePointJoint","acceleration":100,"joint":{"cols":1,"data":{"cols":1,"data":[0.9538992599515632,-2.0013387474756015,2.4008742641025353,0.0,1.1712608101679631,0.16042019343420044],"rows":6},"rows":6},"move_type":"kMoveJ","velocity":100,"zone":100},{"_RESOURCE_":"xyz::motion_solver::ExecutablePointJoint","acceleration":100,"joint":{"cols":1,"data":{"cols":1,"data":[0.9538992599515632,-2.0161091164381686,2.367788437608546,0.0,1.2191170056245202,0.160420193434196],"rows":6},"rows":6},"move_type":"kMoveJ","velocity":100,"zone":100},{"_RESOURCE_":"xyz::motion_solver::ExecutablePointJoint","acceleration":100,"joint":{"cols":1,"data":{"cols":1,"data":[0.9538992599515632,-2.027846791898136,2.3332374691398616,0.0,1.2654056495531716,0.1604201934341991],"rows":6},"rows":6},"move_type":"kMoveJ","velocity":100,"zone":100},{"_RESOURCE_":"xyz::motion_solver::ExecutablePointJoint","acceleration":100,"joint":{"cols":1,"data":{"cols":1,"data":[0.9538992599515632,-2.036767417108209,2.2972940855548245,0.0,1.3102696583482816,0.16042019343419778],"rows":6},"rows":6},"move_type":"kMoveJ","velocity":100,"zone":100},{"_RESOURCE_":"xyz::motion_solver::ExecutablePointJoint","acceleration":100,"joint":{"cols":1,"data":{"cols":1,"data":[0.9538992599515632,-2.0430703931865377,2.2600169406236343,0.0,1.3538497793578008,0.16042019343420044],"rows":6},"rows":6},"move_type":"kMoveJ","velocity":100,"zone":100}]}},{"choice_idx":0,"commands":[{"_RESOURCE_":"EnableCollisionCommand","body_node_path":{"is_absolute":true,"path":["root","WorldFrame","长方体-(3)","Skeleton","BodyNode"]}},{"_RESOURCE_":"SetRobotPositionCommand","prev_robot_joints_":{"cols":1,"data":{"cols":1,"data":[0.9538992599515632,-2.0430703931865377,2.2600169406236343,0.0,1.3538497793578008,0.160420193434192],"rows":6},"rows":6},"robot_joints_":{"cols":1,"data":{"cols":1,"data":[2.4943645892300914,-0.8664707966560754,1.8725876900882863,4.440892098500626e-16,0.5646794333626861,0.13817009903771682],"rows":6},"rows":6}}],"group_idx":0,"milestone_indices":{"cols":1,"data":{"cols":1,"data":[0,1,2,3,4,5,6],"rows":7},"rows":7},"move_type":"kSmartPlanner","name":"slidestart_z","trajectory":{"name":"kSmartPlanner-2026-03-31T09:38:17.418077523+00:00","robot_name":{"brand":"","series":"","variant":""},"waypoints":[{"_RESOURCE_":"xyz::motion_solver::ExecutablePointJoint","acceleration":100,"joint":{"cols":1,"data":{"cols":1,"data":[0.9538992599515632,-2.0430703931865377,2.2600169406236343,0.0,1.3538497793578008,0.16042019343420044],"rows":6},"rows":6},"move_type":"kMoveJ","velocity":100,"zone":100},{"_RESOURCE_":"xyz::motion_solver::ExecutablePointJoint","acceleration":100,"joint":{"cols":1,"data":{"cols":1,"data":[1.488170749414277,-1.795914294594163,2.0759973862978978,-4.26814447738831e-09,1.2907132338283867,0.13467481626358646],"rows":6},"rows":6},"move_type":"kMoveJ","velocity":100,"zone":100},{"_RESOURCE_":"xyz::motion_solver::ExecutablePointJoint","acceleration":100,"joint":{"cols":1,"data":{"cols":1,"data":[1.7014732784260573,-1.6960613672031724,2.0035922122979173,-1.4813867789568955e-08,1.2632654895318844,0.1245146239335714],"rows":6},"rows":6},"move_type":"kMoveJ","velocity":100,"zone":100},{"_RESOURCE_":"xyz::motion_solver::ExecutablePointJoint","acceleration":100,"joint":{"cols":1,"data":{"cols":1,"data":[1.8076507983630914,-1.6449793342279626,1.9687927143166275,-3.0398272553755485e-08,1.2469829702847743,0.11959547939649949],"rows":6},"rows":6},"move_type":"kMoveJ","velocity":100,"zone":100},{"_RESOURCE_":"xyz::motion_solver::ExecutablePointJoint","acceleration":100,"joint":{"cols":1,"data":{"cols":1,"data":[2.090031431655795,-1.3386224571404821,1.9335145251600439,1.1017541984919862e-08,0.9759042825540054,0.12692435138722327],"rows":6},"rows":6},"move_type":"kMoveJ","velocity":100,"zone":100},{"_RESOURCE_":"xyz::motion_solver::ExecutablePointJoint","acceleration":100,"joint":{"cols":1,"data":{"cols":1,"data":[2.359548924649983,-1.023882011759767,1.892927696300217,6.208054030313072e-11,0.7017506422108648,0.13435330712792393],"rows":6},"rows":6},"move_type":"kMoveJ","velocity":100,"zone":100},{"_RESOURCE_":"xyz::motion_solver::ExecutablePointJoint","acceleration":100,"joint":{"cols":1,"data":{"cols":1,"data":[2.4943645892300914,-0.8664707966560754,1.8725876900882863,4.440892098500626e-16,0.5646794333626861,0.13817009903771682],"rows":6},"rows":6},"move_type":"kMoveJ","velocity":100,"zone":100}]}},{"choice_idx":1,"commands":[{"_RESOURCE_":"SetRobotPositionCommand","prev_robot_joints_":{"cols":1,"data":{"cols":1,"data":[2.4943645892300914,-0.8664707966560754,1.8725876900882863,4.440892098500626e-16,0.5646794333626861,0.13817009903771682],"rows":6},"rows":6},"robot_joints_":{"cols":1,"data":{"cols":1,"data":[2.4943645892300914,-0.7707519941812304,1.8552094818241898,4.440892098500626e-16,0.4863388391519381,0.13817009903771504],"rows":6},"rows":6}}],"group_idx":0,"milestone_indices":{"cols":1,"data":{"cols":1,"data":[0,3],"rows":2},"rows":2},"move_type":"kLinear","name":"slidestart","trajectory":{"name":"slidestart","robot_name":{"brand":"","series":"","variant":""},"waypoints":[{"_RESOURCE_":"xyz::motion_solver::ExecutablePointJoint","acceleration":100,"joint":{"cols":1,"data":{"cols":1,"data":[2.4943645892300914,-0.8664707966560754,1.8725876900882863,4.440892098500626e-16,0.5646794333626861,0.13817009903771682],"rows":6},"rows":6},"move_type":"kMoveJ","velocity":100,"zone":100},{"_RESOURCE_":"xyz::motion_solver::ExecutablePointJoint","acceleration":100,"joint":{"cols":1,"data":{"cols":1,"data":[2.4943645892300914,-0.8351722341790819,1.8682004875448435,4.440892098500626e-16,0.5377680734291355,0.1381700990377137],"rows":6},"rows":6},"move_type":"kMoveJ","velocity":100,"zone":100},{"_RESOURCE_":"xyz::motion_solver::ExecutablePointJoint","acceleration":100,"joint":{"cols":1,"data":{"cols":1,"data":[2.4943645892300914,-0.803249601708659,1.8624064143892225,4.440892098500626e-16,0.511639514114334,0.1381700990377137],"rows":6},"rows":6},"move_type":"kMoveJ","velocity":100,"zone":100},{"_RESOURCE_":"xyz::motion_solver::ExecutablePointJoint","acceleration":100,"joint":{"cols":1,"data":{"cols":1,"data":[2.4943645892300914,-0.7707519941812304,1.8552094818241898,4.440892098500626e-16,0.4863388391519381,0.13817009903771504],"rows":6},"rows":6},"move_type":"kMoveJ","velocity":100,"zone":100}]}},{"choice_idx":0,"commands":[{"_RESOURCE_":"SetRobotPositionCommand","prev_robot_joints_":{"cols":1,"data":{"cols":1,"data":[2.4943645892300914,-0.7707519941812304,1.8552094818241898,4.440892098500626e-16,0.4863388391519381,0.13817009903771682],"rows":6},"rows":6},"robot_joints_":{"cols":1,"data":{"cols":1,"data":[2.4943645892300914,-0.7707519941812304,1.8552094818241898,0.0,0.486338839151939,0.13817009903771194],"rows":6},"rows":6}}],"group_idx":0,"milestone_indices":{"cols":1,"data":{"cols":1,"data":[0,1],"rows":2},"rows":2},"move_type":"kJoint","name":"preplace","trajectory":{"name":"preplace","robot_name":{"brand":"","series":"","variant":""},"waypoints":[{"_RESOURCE_":"xyz::motion_solver::ExecutablePointJoint","acceleration":100,"joint":{"cols":1,"data":{"cols":1,"data":[2.4943645892300914,-0.7707519941812304,1.8552094818241898,4.440892098500626e-16,0.4863388391519381,0.13817009903771504],"rows":6},"rows":6},"move_type":"kMoveJ","velocity":100,"zone":100},{"_RESOURCE_":"xyz::motion_solver::ExecutablePointJoint","acceleration":100,"joint":{"cols":1,"data":{"cols":1,"data":[2.4943645892300914,-0.7707519941812304,1.8552094818241898,0.0,0.486338839151939,0.13817009903771194],"rows":6},"rows":6},"move_type":"kMoveJ","velocity":100,"zone":100}]}},{"choice_idx":1,"commands":[{"_RESOURCE_":"SetRobotPositionCommand","prev_robot_joints_":{"cols":1,"data":{"cols":1,"data":[2.4943645892300914,-0.7707519941812304,1.8552094818241898,0.0,0.4863388391519381,0.13817009903771682],"rows":6},"rows":6},"robot_joints_":{"cols":1,"data":{"cols":1,"data":[2.5237902545225026,-0.696489439194182,1.766622862839328,0.0,0.5006629031497511,0.16759576433013734],"rows":6},"rows":6}}],"group_idx":0,"milestone_indices":{"cols":1,"data":{"cols":1,"data":[0,20],"rows":2},"rows":2},"move_type":"kLinear","name":"near_place","trajectory":{"name":"near_place","robot_name":{"brand":"","series":"","variant":""},"waypoints":[{"_RESOURCE_":"xyz::motion_solver::ExecutablePointJoint","acceleration":100,"joint":{"cols":1,"data":{"cols":1,"data":[2.4943645892300914,-0.7707519941812304,1.8552094818241898,0.0,0.486338839151939,0.13817009903771194],"rows":6},"rows":6},"move_type":"kMoveJ","velocity":100,"zone":100},{"_RESOURCE_":"xyz::motion_solver::ExecutablePointJoint","acceleration":100,"joint":{"cols":1,"data":{"cols":1,"data":[2.4958928338826087,-0.767045599845642,1.8509258573137988,0.0,0.48691606932674114,0.1396983436902257],"rows":6},"rows":6},"move_type":"kMoveJ","velocity":100,"zone":100},{"_RESOURCE_":"xyz::motion_solver::ExecutablePointJoint","acceleration":100,"joint":{"cols":1,"data":{"cols":1,"data":[2.497414903949129,-0.7633389190905531,1.8466272499803589,0.0,0.4875079959050921,0.14122041375674677],"rows":6},"rows":6},"move_type":"kMoveJ","velocity":100,"zone":100},{"_RESOURCE_":"xyz::motion_solver::ExecutablePointJoint","acceleration":100,"joint":{"cols":1,"data":{"cols":1,"data":[2.4989308297653157,-0.7596318845302319,1.8423136071776112,0.0,0.4881146041475186,0.1427363395729362],"rows":6},"rows":6},"move_type":"kMoveJ","velocity":100,"zone":100},{"_RESOURCE_":"xyz::motion_solver::ExecutablePointJoint","acceleration":100,"joint":{"cols":1,"data":{"cols":1,"data":[2.500440641535368,-0.7559244280950077,1.8379848748028245,0.0,0.48873588008708113,0.14424615134298957],"rows":6},"rows":6},"move_type":"kMoveJ","velocity":100,"zone":100},{"_RESOURCE_":"xyz::motion_solver::ExecutablePointJoint","acceleration":100,"joint":{"cols":1,"data":{"cols":1,"data":[2.501944369331838,-0.7522164810248184,1.8336409972775716,0.0,0.4893718105421452,0.14574987913945803],"rows":6},"rows":6},"move_type":"kMoveJ","velocity":100,"zone":100},{"_RESOURCE_":"xyz::motion_solver::ExecutablePointJoint","acceleration":100,"joint":{"cols":1,"data":{"cols":1,"data":[2.503442043095463,-0.7485079738623837,1.8292819175279984,4.440892098500626e-16,0.4900223831292827,0.14724755290308655],"rows":6},"rows":6},"move_type":"kMoveJ","velocity":100,"zone":100},{"_RESOURCE_":"xyz::motion_solver::ExecutablePointJoint","acceleration":100,"joint":{"cols":1,"data":{"cols":1,"data":[2.5049336926350163,-0.7447988364459901,1.824907576964569,4.440892098500626e-16,0.4906875862763185,0.14873920244263994],"rows":6},"rows":6},"move_type":"kMoveJ","velocity":100,"zone":100},{"_RESOURCE_":"xyz::motion_solver::ExecutablePointJoint","acceleration":100,"joint":{"cols":1,"data":{"cols":1,"data":[2.506419347627184,-0.7410889979018918,1.820517915461262,4.440892098500626e-16,0.49136740923552713,0.1502248574348113],"rows":6},"rows":6},"move_type":"kMoveJ","velocity":100,"zone":100},{"_RESOURCE_":"xyz::motion_solver::ExecutablePointJoint","acceleration":100,"joint":{"cols":1,"data":{"cols":1,"data":[2.507899037616456,-0.7373783866363119,1.8161128713342176,4.440892098500626e-16,0.4920618420969922,0.15170454742407946],"rows":6},"rows":6},"move_type":"kMoveJ","velocity":100,"zone":100},{"_RESOURCE_":"xyz::motion_solver::ExecutablePointJoint","acceleration":100,"joint":{"cols":1,"data":{"cols":1,"data":[2.5093727920150357,-0.733666930327042,1.8116923813198005,4.440892098500626e-16,0.4927708758021394,0.15317830182265757],"rows":6},"rows":6},"move_type":"kMoveJ","velocity":100,"zone":100},{"_RESOURCE_":"xyz::motion_solver::ExecutablePointJoint","acceleration":100,"joint":{"cols":1,"data":{"cols":1,"data":[2.5108406401027707,-0.7299545559146288,1.8072563805520794,4.440892098500626e-16,0.4934945021574473,0.15464614991039616],"rows":6},"rows":6},"move_type":"kMoveJ","velocity":100,"zone":100},{"_RESOURCE_":"xyz::motion_solver::ExecutablePointJoint","acceleration":100,"joint":{"cols":1,"data":{"cols":1,"data":[2.5123026110270965,-0.7262411895931487,1.8028048025396872,4.440892098500626e-16,0.49423271384835843,0.1561081208347206],"rows":6},"rows":6},"move_type":"kMoveJ","velocity":100,"zone":100},{"_RESOURCE_":"xyz::motion_solver::ExecutablePointJoint","acceleration":100,"joint":{"cols":1,"data":{"cols":1,"data":[2.5137587338030025,-0.7225267568005509,1.7983375791420633,4.440892098500626e-16,0.4949855044533851,0.15756424361062926],"rows":6},"rows":6},"move_type":"kMoveJ","velocity":100,"zone":100},{"_RESOURCE_":"xyz::motion_solver::ExecutablePointJoint","acceleration":100,"joint":{"cols":1,"data":{"cols":1,"data":[2.5152090373130136,-0.718811182208571,1.7938546405450326,4.440892098500626e-16,0.4957528684584358,0.1590145471206399],"rows":6},"rows":6},"move_type":"kMoveJ","velocity":100,"zone":100},{"_RESOURCE_":"xyz::motion_solver::ExecutablePointJoint","acceleration":100,"joint":{"cols":1,"data":{"cols":1,"data":[2.5166535503071827,-0.7150943897121986,1.789355915235733,4.440892098500626e-16,0.4965348012713626,0.16045906011480948],"rows":6},"rows":6},"move_type":"kMoveJ","velocity":100,"zone":100},{"_RESOURCE_":"xyz::motion_solver::ExecutablePointJoint","acceleration":100,"joint":{"cols":1,"data":{"cols":1,"data":[2.5180923014031107,-0.7113763024186968,1.7848413299768415,4.440892098500626e-16,0.4973312992367527,0.16189781121074054],"rows":6},"rows":6},"move_type":"kMoveJ","velocity":100,"zone":100},{"_RESOURCE_":"xyz::motion_solver::ExecutablePointJoint","acceleration":100,"joint":{"cols":1,"data":{"cols":1,"data":[2.51952531908597,-0.70765684263616,1.7803108097800973,4.440892098500626e-16,0.4981423596509602,0.16333082889359707],"rows":6},"rows":6},"move_type":"kMoveJ","velocity":100,"zone":100},{"_RESOURCE_":"xyz::motion_solver::ExecutablePointJoint","acceleration":100,"joint":{"cols":1,"data":{"cols":1,"data":[2.5209526317085507,-0.703935931861599,1.7757642778790892,4.440892098500626e-16,0.4989679807774059,0.16475814151617785],"rows":6},"rows":6},"move_type":"kMoveJ","velocity":100,"zone":100},{"_RESOURCE_":"xyz::motion_solver::ExecutablePointJoint","acceleration":100,"joint":{"cols":1,"data":{"cols":1,"data":[2.5223742674913225,-0.7002134907685491,1.7712016557012955,4.440892098500626e-16,0.49980816186215016,0.16617977729895195],"rows":6},"rows":6},"move_type":"kMoveJ","velocity":100,"zone":100},{"_RESOURCE_":"xyz::motion_solver::ExecutablePointJoint","acceleration":100,"joint":{"cols":1,"data":{"cols":1,"data":[2.5237902545225026,-0.696489439194182,1.766622862839328,0.0,0.5006629031497511,0.16759576433013734],"rows":6},"rows":6},"move_type":"kMoveJ","velocity":100,"zone":100}]}},{"choice_idx":0,"commands":[{"_RESOURCE_":"SetRobotPositionCommand","prev_robot_joints_":{"cols":1,"data":{"cols":1,"data":[2.5237902545225026,-0.696489439194182,1.766622862839328,0.0,0.5006629031497511,0.16759576433013734],"rows":6},"rows":6},"robot_joints_":{"cols":1,"data":{"cols":1,"data":[2.5330878611953587,-0.6765556609700831,1.7372053173617452,0.0,0.510146670403234,0.17689337100299785],"rows":6},"rows":6}}],"group_idx":0,"milestone_indices":{"cols":1,"data":{"cols":1,"data":[0,1],"rows":2},"rows":2},"move_type":"kLinear","name":"place","trajectory":{"name":"place","robot_name":{"brand":"","series":"","variant":""},"waypoints":[{"_RESOURCE_":"xyz::motion_solver::ExecutablePointJoint","acceleration":100,"joint":{"cols":1,"data":{"cols":1,"data":[2.5237902545225026,-0.696489439194182,1.766622862839328,0.0,0.5006629031497511,0.16759576433013734],"rows":6},"rows":6},"move_type":"kMoveJ","velocity":100,"zone":100},{"_RESOURCE_":"xyz::motion_solver::ExecutablePointJoint","acceleration":100,"joint":{"cols":1,"data":{"cols":1,"data":[2.5330878611953587,-0.6765556609700831,1.7372053173617452,0.0,0.510146670403234,0.17689337100299785],"rows":6},"rows":6},"move_type":"kMoveJ","velocity":100,"zone":100}]}},{"choice_idx":0,"commands":[{"_RESOURCE_":"DetachObjectCommand","attachment_info":{"from_workspace_path":{"is_absolute":true,"path":["root","WorldFrame","托盘-(1)","工作空间_1","WorkspaceBody","Workspace","ContainerGroup"]},"object_paths":[{"is_absolute":false,"path":["Box_1774946344618"]}],"reference_object_path":{"is_absolute":false,"path":["Box_1774946344618"]},"tf_tip_reference":{"position":{"x":-0.1280000000000001,"y":-0.12150000000000011,"z":0.12450000000000011},"quaternion":{"w":-1.8055593228630333e-32,"x":1.0000000000000002,"y":-2.081668171172168e-16,"z":1.2325951644078307e-32}},"tip_path":{"is_absolute":false,"path":["工具形态","吸盘基准面","吸取组合","tip_1"]},"to_workspace_path":{"is_absolute":true,"path":["root","WorldFrame","托盘-(3)","工作空间_3","WorkspaceBody","Workspace","ContainerGroup"]}},"children_idx":[0],"children_tfs":[{"position":{"x":-0.1280000000000001,"y":-0.12150000000000005,"z":0.12450000000000011},"quaternion":{"w":0.0,"x":1.0000000000000002,"y":0.0,"z":0.0}}],"tf_new_ws_ref":{"position":{"x":-0.17,"y":0.23500000000000026,"z":0.35150000000000026},"quaternion":{"w":1.0000000000000009,"x":3.0814879110195746e-33,"y":-1.2325951644078299e-31,"z":1.3877787807815085e-17}}},{"_RESOURCE_":"SetRobotPositionCommand","prev_robot_joints_":{"cols":1,"data":{"cols":1,"data":[2.5330878611953587,-0.6765556609700831,1.7372053173617452,0.0,0.510146670403234,0.17689337100299785],"rows":6},"rows":6},"robot_joints_":{"cols":1,"data":{"cols":1,"data":[2.5237902545225026,-0.6964894391941816,1.766622862839327,0.0,0.5006629031497511,0.167595764330132],"rows":6},"rows":6}}],"group_idx":0,"milestone_indices":{"cols":1,"data":{"cols":1,"data":[0,1],"rows":2},"rows":2},"move_type":"kLinear","name":"nearpostplace","trajectory":{"name":"nearpostplace","robot_name":{"brand":"","series":"","variant":""},"waypoints":[{"_RESOURCE_":"xyz::motion_solver::ExecutablePointJoint","acceleration":100,"joint":{"cols":1,"data":{"cols":1,"data":[2.5330878611953587,-0.6765556609700831,1.7372053173617452,0.0,0.510146670403234,0.17689337100299785],"rows":6},"rows":6},"move_type":"kMoveJ","velocity":100,"zone":100},{"_RESOURCE_":"xyz::motion_solver::ExecutablePointJoint","acceleration":100,"joint":{"cols":1,"data":{"cols":1,"data":[2.5237902545225026,-0.6964894391941816,1.766622862839327,0.0,0.5006629031497511,0.167595764330132],"rows":6},"rows":6},"move_type":"kMoveJ","velocity":100,"zone":100}]}},{"choice_idx":0,"commands":[{"_RESOURCE_":"DisableCollisionCommand","body_node_path":{"is_absolute":true,"path":["root","WorldFrame","长方体-(3)","Skeleton","BodyNode"]}},{"_RESOURCE_":"SetRobotPositionCommand","prev_robot_joints_":{"cols":1,"data":{"cols":1,"data":[2.5237902545225026,-0.6964894391941816,1.766622862839327,0.0,0.5006629031497511,0.167595764330132],"rows":6},"rows":6},"robot_joints_":{"cols":1,"data":{"cols":1,"data":[2.4943645892300914,-0.7707519941812313,1.8552094818241898,0.0,0.486338839151939,0.1381700990377137],"rows":6},"rows":6}},{"_RESOURCE_":"SetCollisionTypeCommand","body_node_path":{"is_absolute":true,"path":["root","WorldFrame","托盘-(3)","工作空间_3","WorkspaceBody","Workspace","ContainerGroup","Box_1774946344618","box_body"]},"collision_type":"kOtherObject","prev_collision_type":"kTargetObject"}],"group_idx":0,"milestone_indices":{"cols":1,"data":{"cols":1,"data":[0,2],"rows":2},"rows":2},"move_type":"kLinear","name":"postplace","trajectory":{"name":"postplace","robot_name":{"brand":"","series":"","variant":""},"waypoints":[{"_RESOURCE_":"xyz::motion_solver::ExecutablePointJoint","acceleration":100,"joint":{"cols":1,"data":{"cols":1,"data":[2.5237902545225026,-0.6964894391941816,1.766622862839327,0.0,0.5006629031497511,0.167595764330132],"rows":6},"rows":6},"move_type":"kMoveJ","velocity":100,"zone":100},{"_RESOURCE_":"xyz::motion_solver::ExecutablePointJoint","acceleration":100,"joint":{"cols":1,"data":{"cols":1,"data":[2.5093727920150357,-0.7336669303270416,1.8116923813197996,4.440892098500626e-16,0.4927708758021385,0.15317830182266468],"rows":6},"rows":6},"move_type":"kMoveJ","velocity":100,"zone":100},{"_RESOURCE_":"xyz::motion_solver::ExecutablePointJoint","acceleration":100,"joint":{"cols":1,"data":{"cols":1,"data":[2.4943645892300914,-0.7707519941812313,1.8552094818241898,0.0,0.486338839151939,0.1381700990377137],"rows":6},"rows":6},"move_type":"kMoveJ","velocity":100,"zone":100}]}}]}